contest/TestCase.py
contest/__init__.py
contest/__main__.py
contest/__version__.py
contest/runner.py
contest/utilities/__init__.py
contest/utilities/chdir.py
contest/utilities/configure_yaml.py
contest/utilities/importer.py
contest/utilities/logger.py
contest-2024.8.0.dist-info/LICENSE.md
contest-2024.8.0.dist-info/METADATA
contest-2024.8.0.dist-info/WHEEL
contest-2024.8.0.dist-info/entry_points.txt
contest-2024.8.0.dist-info/top_level.txt
contest-2024.8.0.dist-info/RECORD
