Metadata-Version: 2.1
Name: contest
Version: 2024.8.0
Summary: A console application tester.
Home-page: https://github.com/Lnk2past/contest
Author: Lnk2past
License: MIT
License-File: LICENSE.md
Requires-Dist: Pillow
Requires-Dist: PyYAML
